pedpol/__init__.py
pedpol/core.py
pedpol/generations.py
pedpol/validation.py
pedpol-0.3.1.dist-info/WHEEL
pedpol-0.3.1.dist-info/METADATA
pedpol-0.3.1.dist-info/RECORD
