Metadata-Version: 2.3
Name: pedpol
Version: 0.3.1
Summary: For wrangling animal pedigrees
Requires-Dist: polars>=1.27.1
Requires-Python: >=3.11
